crewai_mcp_server/__init__.py
crewai_mcp_server/docs_fetcher.py
crewai_mcp_server/server.py
crewai_mcp_server-0.1.0.dist-info/METADATA
crewai_mcp_server-0.1.0.dist-info/WHEEL
crewai_mcp_server-0.1.0.dist-info/entry_points.txt
crewai_mcp_server-0.1.0.dist-info/top_level.txt
crewai_mcp_server-0.1.0.dist-info/RECORD
