Metadata-Version: 2.4
Name: crewai-mcp-server
Version: 0.1.0
Summary: MCP server for CrewAI documentation
Author-email: Your Name <your.email@example.com>
Requires-Python: >=3.8
Requires-Dist: mcp>=0.1.0
Requires-Dist: httpx
Requires-Dist: beautifulsoup4
Requires-Dist: markdown
Requires-Dist: asyncio
